tszip/__init__.py
tszip/__main__.py
tszip/_version.py
tszip/cli.py
tszip/compat.py
tszip/compression.py
tszip/exceptions.py
tszip/provenance.py
tszip-0.2.6.dist-info/licenses/LICENSE
tszip-0.2.6.dist-info/METADATA
tszip-0.2.6.dist-info/WHEEL
tszip-0.2.6.dist-info/entry_points.txt
tszip-0.2.6.dist-info/top_level.txt
tszip-0.2.6.dist-info/RECORD
